pydantic2_settings_vault/__init__.py
pydantic2_settings_vault/py.typed
pydantic2_settings_vault-1.1.0.dist-info/METADATA
pydantic2_settings_vault-1.1.0.dist-info/WHEEL
pydantic2_settings_vault-1.1.0.dist-info/licenses/LICENSE
pydantic2_settings_vault-1.1.0.dist-info/RECORD
