Metadata-Version: 2.4
Name: pydantic2-settings-vault
Version: 1.1.0
Summary: A Pydantic v2 settings extension for secure configuration management using HashiCorp Vault OpenSource (OSS) and Enterprise
Project-URL: homepage, https://github.com/sylvainmouquet/pydantic2-settings-vault
Project-URL: documentation, https://github.com/sylvainmouquet/pydantic2-settings-vault
Project-URL: repository, https://github.com/sylvainmouquet/pydantic2-settings-vault
Project-URL: changelog, https://github.com/sylvainmouquet/pydantic2-settings-vault/releases
Author-email: Sylvain Mouquet <sylvain.mouquet@gmail.com>
License: MIT
License-File: LICENSE
Keywords: configuration,enterprise,hashicorp,opensource,pydantic,python,secrets management,security,settings,vault
Classifier: Development Status :: 5 - Production/Stable
Classifier: Intended Audience :: Developers
Classifier: License :: OSI Approved :: MIT License
Classifier: Programming Language :: Python
Classifier: Programming Language :: Python :: 3
Classifier: Programming Language :: Python :: 3.10
Classifier: Programming Language :: Python :: 3.11
Classifier: Programming Language :: Python :: 3.12
Classifier: Programming Language :: Python :: 3.13
Classifier: Topic :: Software Development :: Libraries :: Python Modules
Requires-Python: >=3.10
Requires-Dist: aiohttp>=3.10.10
Requires-Dist: certifi>=2025.1.31
Requires-Dist: concurrency-limiter>=1.1.0
Requires-Dist: pydantic-settings>=2.6.0
Requires-Dist: pydantic>=2.9.2
Requires-Dist: reattempt>=1.1.3
